webbrowser.py
_pyodide/__init__.py
_pyodide/_base.py
_pyodide/_core_docs.py
_pyodide/_future_helper.py
_pyodide/_importhook.py
_pyodide/docs_argspec.py
_pyodide/docstring.py
_pyodide/jsbind.py
_pyodide/py.typed
pyodide/__init__.py
pyodide/_core.py
pyodide/_package_loader.py
pyodide/_run_js.py
pyodide/_state.py
pyodide/code.py
pyodide/common.py
pyodide/console.py
pyodide/py.typed
pyodide/webloop.py
pyodide/ffi/__init__.py
pyodide/ffi/wrappers.py
pyodide/http/__init__.py
pyodide/http/_exceptions.py
pyodide/http/_pyfetch.py
pyodide/http/pyxhr.py
pyodide_py-0.29.1.dist-info/METADATA
pyodide_py-0.29.1.dist-info/WHEEL
pyodide_py-0.29.1.dist-info/top_level.txt
pyodide_py-0.29.1.dist-info/RECORD
